sisyphus_control/__init__.py
sisyphus_control/data.py
sisyphus_control/log.py
sisyphus_control/playlist.py
sisyphus_control/py.typed
sisyphus_control/sisbot_json.py
sisyphus_control/table.py
sisyphus_control/track.py
sisyphus_control/transport.py
sisyphus_control/util.py
sisyphus_control-3.1.3.dist-info/LICENSE
sisyphus_control-3.1.3.dist-info/METADATA
sisyphus_control-3.1.3.dist-info/WHEEL
sisyphus_control-3.1.3.dist-info/top_level.txt
sisyphus_control-3.1.3.dist-info/RECORD
