Metadata-Version: 2.1
Name: sisyphus-control
Version: 3.1.3
Summary: Control your Sisyphus kinetic art tables (sisyphus-industries.com)
Home-page: https://github.com/jkeljo/sisyphus-control
Author: Jonathan Keljo
Keywords: sisyphus
Classifier: Development Status :: 4 - Beta
Classifier: Intended Audience :: Developers
Classifier: Topic :: Home Automation
Classifier: License :: OSI Approved :: MIT License
Classifier: Programming Language :: Python :: 3.8
Requires-Python: >=3.8
License-File: LICENSE
Requires-Dist: aiohttp
Requires-Dist: netifaces
Requires-Dist: python-socketio (<5.0,>=4.0)
Requires-Dist: python-engineio (<4.0,>=3.0)
